[
    {
        "ProviderHotelId": "10284619",
        "ProviderFamily": "Agoda",
        "ProviderLocationCode": null
    },
    {
        "ProviderHotelId": "1504267",
        "ProviderFamily": "EAN",
        "ProviderLocationCode": null
    },
    {
        "ProviderHotelId": "1205105",
        "ProviderFamily": "GRNConnect",
        "ProviderLocationCode": null
    },
    {
        "ProviderHotelId": "675942",
        "ProviderFamily": "GoGlobal",
        "ProviderLocationCode": null
    },
    {
        "ProviderHotelId": "90703",
        "ProviderFamily": "HotelBeds",
        "ProviderLocationCode": "PUY"
    },
    {
        "ProviderHotelId": "HR10000723",
        "ProviderFamily": "MGHoliday",
        "ProviderLocationCode": "HR-RVJ"
    },
    {
        "ProviderHotelId": "4BSt",
        "ProviderFamily": "Rakuten",
        "ProviderLocationCode": null
    },
    {
        "ProviderHotelId": "88267",
        "ProviderFamily": "Stuba",
        "ProviderLocationCode": "16155"
    }
]