[
    {
        "ProviderHotelId": "10278027",
        "ProviderFamily": "Agoda",
        "ProviderLocationCode": null
    },
    {
        "ProviderHotelId": "597085",
        "ProviderFamily": "DOTW",
        "ProviderLocationCode": "13154"
    },
    {
        "ProviderHotelId": "4433525",
        "ProviderFamily": "EAN",
        "ProviderLocationCode": null
    },
    {
        "ProviderHotelId": "1743846",
        "ProviderFamily": "GRNConnect",
        "ProviderLocationCode": null
    },
    {
        "ProviderHotelId": "164428",
        "ProviderFamily": "GoGlobal",
        "ProviderLocationCode": null
    },
    {
        "ProviderHotelId": "150856",
        "ProviderFamily": "HotelBeds",
        "ProviderLocationCode": "MAD"
    },
    {
        "ProviderHotelId": "ES10008498",
        "ProviderFamily": "MGHoliday",
        "ProviderLocationCode": "ES-MAD"
    },
    {
        "ProviderHotelId": "ANBl",
        "ProviderFamily": "Rakuten",
        "ProviderLocationCode": null
    },
    {
        "ProviderHotelId": "438914",
        "ProviderFamily": "Restel",
        "ProviderLocationCode": "885"
    },
    {
        "ProviderHotelId": "7172808",
        "ProviderFamily": "Stuba",
        "ProviderLocationCode": "18417"
    },
    {
        "ProviderHotelId": "1161395",
        "ProviderFamily": "TBO",
        "ProviderLocationCode": "243021"
    }
]