[
    {
        "ProviderHotelId": "10281372",
        "ProviderFamily": "Agoda",
        "ProviderLocationCode": null
    },
    {
        "ProviderHotelId": "5020785",
        "ProviderFamily": "DOTW",
        "ProviderLocationCode": "13354"
    },
    {
        "ProviderHotelId": "46147393",
        "ProviderFamily": "EAN",
        "ProviderLocationCode": null
    },
    {
        "ProviderHotelId": "1336400",
        "ProviderFamily": "GoGlobal",
        "ProviderLocationCode": null
    },
    {
        "ProviderHotelId": "228466",
        "ProviderFamily": "HotelBeds",
        "ProviderLocationCode": "SVQ"
    },
    {
        "ProviderHotelId": "ES10014887",
        "ProviderFamily": "MGHoliday",
        "ProviderLocationCode": "ES-SVQ"
    },
    {
        "ProviderHotelId": "TUtd",
        "ProviderFamily": "Rakuten",
        "ProviderLocationCode": null
    },
    {
        "ProviderHotelId": "C37341",
        "ProviderFamily": "Restel",
        "ProviderLocationCode": "225"
    },
    {
        "ProviderHotelId": "1197343",
        "ProviderFamily": "TBO",
        "ProviderLocationCode": "137558"
    }
]