[
    {
        "ProviderHotelId": "1056370",
        "ProviderFamily": "Agoda",
        "ProviderLocationCode": null
    },
    {
        "ProviderHotelId": "27594919",
        "ProviderFamily": "EAN",
        "ProviderLocationCode": null
    },
    {
        "ProviderHotelId": "1665365",
        "ProviderFamily": "GRNConnect",
        "ProviderLocationCode": null
    },
    {
        "ProviderHotelId": "1852921",
        "ProviderFamily": "TBO",
        "ProviderLocationCode": "142322"
    }
]