[
    {
        "ProviderHotelId": "103394",
        "ProviderFamily": "Agoda",
        "ProviderLocationCode": null
    },
    {
        "ProviderHotelId": "794575",
        "ProviderFamily": "DOTW",
        "ProviderLocationCode": "69056"
    },
    {
        "ProviderHotelId": "8537",
        "ProviderFamily": "EAN",
        "ProviderLocationCode": null
    },
    {
        "ProviderHotelId": "1882748",
        "ProviderFamily": "GRNConnect",
        "ProviderLocationCode": null
    },
    {
        "ProviderHotelId": "78259",
        "ProviderFamily": "GoGlobal",
        "ProviderLocationCode": null
    },
    {
        "ProviderHotelId": "602488",
        "ProviderFamily": "HotelBeds",
        "ProviderLocationCode": "MSP"
    },
    {
        "ProviderHotelId": "US10002778",
        "ProviderFamily": "MGHoliday",
        "ProviderLocationCode": "US-347"
    },
    {
        "ProviderHotelId": "TBra",
        "ProviderFamily": "Rakuten",
        "ProviderLocationCode": null
    },
    {
        "ProviderHotelId": "395351936",
        "ProviderFamily": "Stuba",
        "ProviderLocationCode": "394098031"
    },
    {
        "ProviderHotelId": "1334918",
        "ProviderFamily": "TBO",
        "ProviderLocationCode": "100513"
    }
]