[
    {
        "ProviderHotelId": "102530",
        "ProviderFamily": "Agoda",
        "ProviderLocationCode": null
    },
    {
        "ProviderHotelId": "793665",
        "ProviderFamily": "DOTW",
        "ProviderLocationCode": "82156"
    },
    {
        "ProviderHotelId": "554211",
        "ProviderFamily": "EAN",
        "ProviderLocationCode": null
    },
    {
        "ProviderHotelId": "1926954",
        "ProviderFamily": "GRNConnect",
        "ProviderLocationCode": null
    },
    {
        "ProviderHotelId": "127278",
        "ProviderFamily": "GoGlobal",
        "ProviderLocationCode": null
    },
    {
        "ProviderHotelId": "276024",
        "ProviderFamily": "HotelBeds",
        "ProviderLocationCode": "BTL"
    },
    {
        "ProviderHotelId": "US10022692",
        "ProviderFamily": "MGHoliday",
        "ProviderLocationCode": "US-13933"
    },
    {
        "ProviderHotelId": "720g",
        "ProviderFamily": "Rakuten",
        "ProviderLocationCode": null
    },
    {
        "ProviderHotelId": "898356",
        "ProviderFamily": "Restel",
        "ProviderLocationCode": "98718"
    },
    {
        "ProviderHotelId": "1337051",
        "ProviderFamily": "TBO",
        "ProviderLocationCode": "126446"
    }
]