[
    {
        "ProviderHotelId": "1002779",
        "ProviderFamily": "Agoda",
        "ProviderLocationCode": null
    },
    {
        "ProviderHotelId": "3979765",
        "ProviderFamily": "DOTW",
        "ProviderLocationCode": "145755"
    },
    {
        "ProviderHotelId": "12923159",
        "ProviderFamily": "EAN",
        "ProviderLocationCode": null
    },
    {
        "ProviderHotelId": "1571617",
        "ProviderFamily": "GRNConnect",
        "ProviderLocationCode": null
    },
    {
        "ProviderHotelId": "482858",
        "ProviderFamily": "GoGlobal",
        "ProviderLocationCode": null
    },
    {
        "ProviderHotelId": "EVIW",
        "ProviderFamily": "Rakuten",
        "ProviderLocationCode": null
    },
    {
        "ProviderHotelId": "439833116",
        "ProviderFamily": "Stuba",
        "ProviderLocationCode": "740559"
    },
    {
        "ProviderHotelId": "1616753",
        "ProviderFamily": "TBO",
        "ProviderLocationCode": "142266"
    }
]