[
    {
        "ProviderHotelId": "10286480",
        "ProviderFamily": "Agoda",
        "ProviderLocationCode": null
    },
    {
        "ProviderHotelId": "2093055",
        "ProviderFamily": "DOTW",
        "ProviderLocationCode": "11674"
    },
    {
        "ProviderHotelId": "1575308",
        "ProviderFamily": "GRNConnect",
        "ProviderLocationCode": null
    },
    {
        "ProviderHotelId": "LT10000047",
        "ProviderFamily": "MGHoliday",
        "ProviderLocationCode": "LT-KUN"
    },
    {
        "ProviderHotelId": "w1iv",
        "ProviderFamily": "Rakuten",
        "ProviderLocationCode": null
    },
    {
        "ProviderHotelId": "965302",
        "ProviderFamily": "Restel",
        "ProviderLocationCode": "27398"
    },
    {
        "ProviderHotelId": "100912094",
        "ProviderFamily": "Stuba",
        "ProviderLocationCode": "17361"
    },
    {
        "ProviderHotelId": "1341379",
        "ProviderFamily": "TBO",
        "ProviderLocationCode": "123639"
    }
]