[
    {
        "ProviderHotelId": "10280670",
        "ProviderFamily": "Agoda",
        "ProviderLocationCode": null
    },
    {
        "ProviderHotelId": "2539643",
        "ProviderFamily": "EAN",
        "ProviderLocationCode": null
    },
    {
        "ProviderHotelId": "1838568",
        "ProviderFamily": "GRNConnect",
        "ProviderLocationCode": null
    },
    {
        "ProviderHotelId": "1338429",
        "ProviderFamily": "TBO",
        "ProviderLocationCode": "116286"
    }
]