[
    {
        "ProviderHotelId": "1010854",
        "ProviderFamily": "Agoda",
        "ProviderLocationCode": null
    },
    {
        "ProviderHotelId": "1772378",
        "ProviderFamily": "DOTW",
        "ProviderLocationCode": "9344"
    },
    {
        "ProviderHotelId": "11007161",
        "ProviderFamily": "EAN",
        "ProviderLocationCode": null
    },
    {
        "ProviderHotelId": "1351826",
        "ProviderFamily": "GRNConnect",
        "ProviderLocationCode": null
    },
    {
        "ProviderHotelId": "328613",
        "ProviderFamily": "GoGlobal",
        "ProviderLocationCode": null
    },
    {
        "ProviderHotelId": "GR10000876",
        "ProviderFamily": "MGHoliday",
        "ProviderLocationCode": "GR-CFU"
    },
    {
        "ProviderHotelId": "RC21",
        "ProviderFamily": "Rakuten",
        "ProviderLocationCode": null
    },
    {
        "ProviderHotelId": "1671376",
        "ProviderFamily": "TBO",
        "ProviderLocationCode": "115291"
    }
]