[
    {
        "ProviderHotelId": "101661",
        "ProviderFamily": "Agoda",
        "ProviderLocationCode": null
    },
    {
        "ProviderHotelId": "726345",
        "ProviderFamily": "DOTW",
        "ProviderLocationCode": "112695"
    },
    {
        "ProviderHotelId": "1691451",
        "ProviderFamily": "EAN",
        "ProviderLocationCode": null
    },
    {
        "ProviderHotelId": "1955262",
        "ProviderFamily": "GRNConnect",
        "ProviderLocationCode": null
    },
    {
        "ProviderHotelId": "102458",
        "ProviderFamily": "GoGlobal",
        "ProviderLocationCode": null
    },
    {
        "ProviderHotelId": "123138",
        "ProviderFamily": "HotelBeds",
        "ProviderLocationCode": "SGU"
    },
    {
        "ProviderHotelId": "US10032670",
        "ProviderFamily": "MGHoliday",
        "ProviderLocationCode": "US-14712"
    },
    {
        "ProviderHotelId": "XiFb",
        "ProviderFamily": "Rakuten",
        "ProviderLocationCode": null
    },
    {
        "ProviderHotelId": "162246",
        "ProviderFamily": "Restel",
        "ProviderLocationCode": "93460"
    },
    {
        "ProviderHotelId": "1228583",
        "ProviderFamily": "TBO",
        "ProviderLocationCode": "148010"
    }
]