[
    {
        "ProviderHotelId": "1006447",
        "ProviderFamily": "Agoda",
        "ProviderLocationCode": null
    },
    {
        "ProviderHotelId": "1212195",
        "ProviderFamily": "GRNConnect",
        "ProviderLocationCode": null
    },
    {
        "ProviderHotelId": "VHcR",
        "ProviderFamily": "Rakuten",
        "ProviderLocationCode": null
    },
    {
        "ProviderHotelId": "1685562",
        "ProviderFamily": "TBO",
        "ProviderLocationCode": "144608"
    }
]