[
    {
        "ProviderHotelId": "10283406",
        "ProviderFamily": "Agoda",
        "ProviderLocationCode": null
    },
    {
        "ProviderHotelId": "1731392",
        "ProviderFamily": "GRNConnect",
        "ProviderLocationCode": null
    },
    {
        "ProviderHotelId": "A42548",
        "ProviderFamily": "Restel",
        "ProviderLocationCode": "1092"
    },
    {
        "ProviderHotelId": "1347924",
        "ProviderFamily": "TBO",
        "ProviderLocationCode": "113248"
    }
]