[
    {
        "ProviderHotelId": "10264889",
        "ProviderFamily": "Agoda",
        "ProviderLocationCode": null
    },
    {
        "ProviderHotelId": "1129228",
        "ProviderFamily": "DOTW",
        "ProviderLocationCode": "11874"
    },
    {
        "ProviderHotelId": "1256841",
        "ProviderFamily": "EAN",
        "ProviderLocationCode": null
    },
    {
        "ProviderHotelId": "1617220",
        "ProviderFamily": "GRNConnect",
        "ProviderLocationCode": null
    },
    {
        "ProviderHotelId": "280319",
        "ProviderFamily": "GoGlobal",
        "ProviderLocationCode": null
    },
    {
        "ProviderHotelId": "650207",
        "ProviderFamily": "HotelBeds",
        "ProviderLocationCode": "HAG"
    },
    {
        "ProviderHotelId": "NL10001512",
        "ProviderFamily": "MGHoliday",
        "ProviderLocationCode": "NL-THE"
    },
    {
        "ProviderHotelId": "SlN7",
        "ProviderFamily": "Rakuten",
        "ProviderLocationCode": null
    },
    {
        "ProviderHotelId": "076165",
        "ProviderFamily": "Restel",
        "ProviderLocationCode": "1358"
    },
    {
        "ProviderHotelId": "56292141",
        "ProviderFamily": "Stuba",
        "ProviderLocationCode": "17672"
    },
    {
        "ProviderHotelId": "1337108",
        "ProviderFamily": "TBO",
        "ProviderLocationCode": "139741"
    }
]