[
    {
        "ProviderHotelId": "10251957",
        "ProviderFamily": "Agoda",
        "ProviderLocationCode": null
    },
    {
        "ProviderHotelId": "4674665",
        "ProviderFamily": "DOTW",
        "ProviderLocationCode": "20274"
    },
    {
        "ProviderHotelId": "44218164",
        "ProviderFamily": "EAN",
        "ProviderLocationCode": null
    },
    {
        "ProviderHotelId": "2164283",
        "ProviderFamily": "GRNConnect",
        "ProviderLocationCode": null
    },
    {
        "ProviderHotelId": "1204819",
        "ProviderFamily": "GoGlobal",
        "ProviderLocationCode": null
    },
    {
        "ProviderHotelId": "934702",
        "ProviderFamily": "HotelBeds",
        "ProviderLocationCode": "PEK"
    },
    {
        "ProviderHotelId": "zvov",
        "ProviderFamily": "Rakuten",
        "ProviderLocationCode": null
    },
    {
        "ProviderHotelId": "6095559",
        "ProviderFamily": "TBO",
        "ProviderLocationCode": "144154"
    }
]