[
    {
        "ProviderHotelId": "10544489",
        "ProviderFamily": "Agoda",
        "ProviderLocationCode": null
    },
    {
        "ProviderHotelId": "2646445",
        "ProviderFamily": "DOTW",
        "ProviderLocationCode": "23074"
    },
    {
        "ProviderHotelId": "42358353",
        "ProviderFamily": "EAN",
        "ProviderLocationCode": null
    },
    {
        "ProviderHotelId": "2114683",
        "ProviderFamily": "GRNConnect",
        "ProviderLocationCode": null
    },
    {
        "ProviderHotelId": "5802364",
        "ProviderFamily": "TBO",
        "ProviderLocationCode": "150281"
    }
]