[
    {
        "ProviderHotelId": "1043990",
        "ProviderFamily": "Agoda",
        "ProviderLocationCode": null
    },
    {
        "ProviderHotelId": "35301133",
        "ProviderFamily": "EAN",
        "ProviderLocationCode": null
    },
    {
        "ProviderHotelId": "2051387",
        "ProviderFamily": "GRNConnect",
        "ProviderLocationCode": null
    },
    {
        "ProviderHotelId": "5277673",
        "ProviderFamily": "TBO",
        "ProviderLocationCode": "107413"
    }
]