[
    {
        "ProviderHotelId": "10265234",
        "ProviderFamily": "Agoda",
        "ProviderLocationCode": null
    },
    {
        "ProviderHotelId": "4650785",
        "ProviderFamily": "DOTW",
        "ProviderLocationCode": "14214"
    },
    {
        "ProviderHotelId": "35367271",
        "ProviderFamily": "EAN",
        "ProviderLocationCode": null
    },
    {
        "ProviderHotelId": "1832438",
        "ProviderFamily": "GRNConnect",
        "ProviderLocationCode": null
    },
    {
        "ProviderHotelId": "611131",
        "ProviderFamily": "GoGlobal",
        "ProviderLocationCode": null
    },
    {
        "ProviderHotelId": "660309",
        "ProviderFamily": "HotelBeds",
        "ProviderLocationCode": "IST"
    },
    {
        "ProviderHotelId": "ZT6t",
        "ProviderFamily": "Rakuten",
        "ProviderLocationCode": null
    },
    {
        "ProviderHotelId": "5003231",
        "ProviderFamily": "TBO",
        "ProviderLocationCode": "122727"
    }
]