[
    {
        "ProviderHotelId": "1043992",
        "ProviderFamily": "Agoda",
        "ProviderLocationCode": null
    },
    {
        "ProviderHotelId": "1959775",
        "ProviderFamily": "DOTW",
        "ProviderLocationCode": "9344"
    },
    {
        "ProviderHotelId": "1353507",
        "ProviderFamily": "GRNConnect",
        "ProviderLocationCode": null
    },
    {
        "ProviderHotelId": "1145074",
        "ProviderFamily": "TBO",
        "ProviderLocationCode": "350950"
    }
]