[
    {
        "ProviderHotelId": "10304115",
        "ProviderFamily": "Agoda",
        "ProviderLocationCode": null
    },
    {
        "ProviderHotelId": "4966165",
        "ProviderFamily": "DOTW",
        "ProviderLocationCode": "114805"
    },
    {
        "ProviderHotelId": "42585040",
        "ProviderFamily": "EAN",
        "ProviderLocationCode": null
    },
    {
        "ProviderHotelId": "2157023",
        "ProviderFamily": "GRNConnect",
        "ProviderLocationCode": null
    },
    {
        "ProviderHotelId": "1241489",
        "ProviderFamily": "GoGlobal",
        "ProviderLocationCode": null
    },
    {
        "ProviderHotelId": "1333786",
        "ProviderFamily": "GoGlobal",
        "ProviderLocationCode": null
    },
    {
        "ProviderHotelId": "QchN",
        "ProviderFamily": "Rakuten",
        "ProviderLocationCode": null
    },
    {
        "ProviderHotelId": "CE1872",
        "ProviderFamily": "Restel",
        "ProviderLocationCode": "35584"
    },
    {
        "ProviderHotelId": "5022146",
        "ProviderFamily": "TBO",
        "ProviderLocationCode": "131852"
    }
]