[
    {
        "ProviderHotelId": "10562778",
        "ProviderFamily": "Agoda",
        "ProviderLocationCode": null
    },
    {
        "ProviderHotelId": "1058691",
        "ProviderFamily": "GRNConnect",
        "ProviderLocationCode": null
    },
    {
        "ProviderHotelId": "229276",
        "ProviderFamily": "HotelBeds",
        "ProviderLocationCode": "BDA"
    },
    {
        "ProviderHotelId": "BM10000009",
        "ProviderFamily": "MGHoliday",
        "ProviderLocationCode": "BM-HMN"
    },
    {
        "ProviderHotelId": "993271",
        "ProviderFamily": "Restel",
        "ProviderLocationCode": "49254"
    },
    {
        "ProviderHotelId": "26333442",
        "ProviderFamily": "Stuba",
        "ProviderLocationCode": "157827"
    },
    {
        "ProviderHotelId": "1127221",
        "ProviderFamily": "TBO",
        "ProviderLocationCode": "120463"
    }
]