[
    {
        "ProviderHotelId": "10265028",
        "ProviderFamily": "Agoda",
        "ProviderLocationCode": null
    },
    {
        "ProviderHotelId": "525765",
        "ProviderFamily": "DOTW",
        "ProviderLocationCode": "12764"
    },
    {
        "ProviderHotelId": "1671493",
        "ProviderFamily": "EAN",
        "ProviderLocationCode": null
    },
    {
        "ProviderHotelId": "1726262",
        "ProviderFamily": "GRNConnect",
        "ProviderLocationCode": null
    },
    {
        "ProviderHotelId": "154663",
        "ProviderFamily": "GoGlobal",
        "ProviderLocationCode": null
    },
    {
        "ProviderHotelId": "23289",
        "ProviderFamily": "GoGlobal",
        "ProviderLocationCode": null
    },
    {
        "ProviderHotelId": "478592",
        "ProviderFamily": "GoGlobal",
        "ProviderLocationCode": null
    },
    {
        "ProviderHotelId": "3695",
        "ProviderFamily": "HotelBeds",
        "ProviderLocationCode": "ALC"
    },
    {
        "ProviderHotelId": "ES10001086",
        "ProviderFamily": "MGHoliday",
        "ProviderLocationCode": "ES-ALC"
    },
    {
        "ProviderHotelId": "a2EP",
        "ProviderFamily": "Rakuten",
        "ProviderLocationCode": null
    },
    {
        "ProviderHotelId": "601652",
        "ProviderFamily": "Restel",
        "ProviderLocationCode": "1176"
    },
    {
        "ProviderHotelId": "49374",
        "ProviderFamily": "Stuba",
        "ProviderLocationCode": "18337"
    },
    {
        "ProviderHotelId": "1039352",
        "ProviderFamily": "TBO",
        "ProviderLocationCode": "100846"
    }
]