[
    {
        "ProviderHotelId": "103683",
        "ProviderFamily": "Agoda",
        "ProviderLocationCode": null
    },
    {
        "ProviderHotelId": "808715",
        "ProviderFamily": "DOTW",
        "ProviderLocationCode": "76166"
    },
    {
        "ProviderHotelId": "522580",
        "ProviderFamily": "EAN",
        "ProviderLocationCode": null
    },
    {
        "ProviderHotelId": "1907167",
        "ProviderFamily": "GRNConnect",
        "ProviderLocationCode": null
    },
    {
        "ProviderHotelId": "132420",
        "ProviderFamily": "GoGlobal",
        "ProviderLocationCode": null
    },
    {
        "ProviderHotelId": "586638",
        "ProviderFamily": "HotelBeds",
        "ProviderLocationCode": "NK1"
    },
    {
        "ProviderHotelId": "US10011925",
        "ProviderFamily": "MGHoliday",
        "ProviderLocationCode": "US-18231"
    },
    {
        "ProviderHotelId": "S8VV",
        "ProviderFamily": "Rakuten",
        "ProviderLocationCode": null
    },
    {
        "ProviderHotelId": "914649",
        "ProviderFamily": "Restel",
        "ProviderLocationCode": "19045"
    },
    {
        "ProviderHotelId": "365591093",
        "ProviderFamily": "Stuba",
        "ProviderLocationCode": "19957"
    },
    {
        "ProviderHotelId": "1334228",
        "ProviderFamily": "TBO",
        "ProviderLocationCode": "118219"
    }
]