[
    {
        "ProviderHotelId": "100403",
        "ProviderFamily": "Agoda",
        "ProviderLocationCode": null
    },
    {
        "ProviderHotelId": "1287218",
        "ProviderFamily": "DOTW",
        "ProviderLocationCode": "70026"
    },
    {
        "ProviderHotelId": "459526",
        "ProviderFamily": "EAN",
        "ProviderLocationCode": null
    },
    {
        "ProviderHotelId": "240252",
        "ProviderFamily": "GoGlobal",
        "ProviderLocationCode": null
    },
    {
        "ProviderHotelId": "667373",
        "ProviderFamily": "HotelBeds",
        "ProviderLocationCode": "FNT"
    },
    {
        "ProviderHotelId": "US10042168",
        "ProviderFamily": "MGHoliday",
        "ProviderLocationCode": "US-8076"
    },
    {
        "ProviderHotelId": "ym0q",
        "ProviderFamily": "Rakuten",
        "ProviderLocationCode": null
    },
    {
        "ProviderHotelId": "1272406",
        "ProviderFamily": "TBO",
        "ProviderLocationCode": "135239"
    }
]