[
    {
        "ProviderHotelId": "10257468",
        "ProviderFamily": "Agoda",
        "ProviderLocationCode": null
    },
    {
        "ProviderHotelId": "29292717",
        "ProviderFamily": "EAN",
        "ProviderLocationCode": null
    },
    {
        "ProviderHotelId": "1031018",
        "ProviderFamily": "GRNConnect",
        "ProviderLocationCode": null
    },
    {
        "ProviderHotelId": "629465",
        "ProviderFamily": "GoGlobal",
        "ProviderLocationCode": null
    },
    {
        "ProviderHotelId": "AT10000133",
        "ProviderFamily": "MGHoliday",
        "ProviderLocationCode": "AT-BAG"
    },
    {
        "ProviderHotelId": "nfW4",
        "ProviderFamily": "Rakuten",
        "ProviderLocationCode": null
    },
    {
        "ProviderHotelId": "CE0863",
        "ProviderFamily": "Restel",
        "ProviderLocationCode": "95474"
    },
    {
        "ProviderHotelId": "1850599",
        "ProviderFamily": "TBO",
        "ProviderLocationCode": "112590"
    }
]