[
    {
        "ProviderHotelId": "1037890",
        "ProviderFamily": "Agoda",
        "ProviderLocationCode": null
    },
    {
        "ProviderHotelId": "3594725",
        "ProviderFamily": "DOTW",
        "ProviderLocationCode": "22744"
    },
    {
        "ProviderHotelId": "16176251",
        "ProviderFamily": "EAN",
        "ProviderLocationCode": null
    },
    {
        "ProviderHotelId": "1820295",
        "ProviderFamily": "GRNConnect",
        "ProviderLocationCode": null
    },
    {
        "ProviderHotelId": "TH10007764",
        "ProviderFamily": "MGHoliday",
        "ProviderLocationCode": "TH-CNX"
    },
    {
        "ProviderHotelId": "cFiJ",
        "ProviderFamily": "Rakuten",
        "ProviderLocationCode": null
    },
    {
        "ProviderHotelId": "1510721",
        "ProviderFamily": "TBO",
        "ProviderLocationCode": "114978"
    }
]