[
    {
        "ProviderHotelId": "1039839",
        "ProviderFamily": "Agoda",
        "ProviderLocationCode": null
    },
    {
        "ProviderHotelId": "1807238",
        "ProviderFamily": "DOTW",
        "ProviderLocationCode": "94036"
    },
    {
        "ProviderHotelId": "11854835",
        "ProviderFamily": "EAN",
        "ProviderLocationCode": null
    },
    {
        "ProviderHotelId": "1934652",
        "ProviderFamily": "GRNConnect",
        "ProviderLocationCode": null
    },
    {
        "ProviderHotelId": "365003",
        "ProviderFamily": "GoGlobal",
        "ProviderLocationCode": null
    },
    {
        "ProviderHotelId": "819034",
        "ProviderFamily": "GoGlobal",
        "ProviderLocationCode": null
    },
    {
        "ProviderHotelId": "690228",
        "ProviderFamily": "HotelBeds",
        "ProviderLocationCode": "NYC"
    },
    {
        "ProviderHotelId": "US10005118",
        "ProviderFamily": "MGHoliday",
        "ProviderLocationCode": "US-8518"
    },
    {
        "ProviderHotelId": "VMOe",
        "ProviderFamily": "Rakuten",
        "ProviderLocationCode": null
    },
    {
        "ProviderHotelId": "A62244",
        "ProviderFamily": "Restel",
        "ProviderLocationCode": "469"
    },
    {
        "ProviderHotelId": "131472172",
        "ProviderFamily": "Stuba",
        "ProviderLocationCode": "19793"
    },
    {
        "ProviderHotelId": "1443435",
        "ProviderFamily": "TBO",
        "ProviderLocationCode": "130452"
    }
]