[
    {
        "ProviderHotelId": "103885",
        "ProviderFamily": "Agoda",
        "ProviderLocationCode": null
    },
    {
        "ProviderHotelId": "796385",
        "ProviderFamily": "DOTW",
        "ProviderLocationCode": "39732"
    },
    {
        "ProviderHotelId": "63529",
        "ProviderFamily": "EAN",
        "ProviderLocationCode": null
    },
    {
        "ProviderHotelId": "1249230",
        "ProviderFamily": "GRNConnect",
        "ProviderLocationCode": null
    },
    {
        "ProviderHotelId": "691590",
        "ProviderFamily": "GoGlobal",
        "ProviderLocationCode": null
    },
    {
        "ProviderHotelId": "77805",
        "ProviderFamily": "GoGlobal",
        "ProviderLocationCode": null
    },
    {
        "ProviderHotelId": "175741",
        "ProviderFamily": "HotelBeds",
        "ProviderLocationCode": "LTQ"
    },
    {
        "ProviderHotelId": "FR10013767",
        "ProviderFamily": "MGHoliday",
        "ProviderLocationCode": "FR-LTQ"
    },
    {
        "ProviderHotelId": "FR10013769",
        "ProviderFamily": "MGHoliday",
        "ProviderLocationCode": "FR-LTQ"
    },
    {
        "ProviderHotelId": "DeyE",
        "ProviderFamily": "Rakuten",
        "ProviderLocationCode": null
    },
    {
        "ProviderHotelId": "898105",
        "ProviderFamily": "Restel",
        "ProviderLocationCode": "134302"
    },
    {
        "ProviderHotelId": "1122615",
        "ProviderFamily": "TBO",
        "ProviderLocationCode": "153562"
    }
]