[
    {
        "ProviderHotelId": "1019907",
        "ProviderFamily": "Agoda",
        "ProviderLocationCode": null
    },
    {
        "ProviderHotelId": "2020555",
        "ProviderFamily": "DOTW",
        "ProviderLocationCode": "18934"
    },
    {
        "ProviderHotelId": "1013179",
        "ProviderFamily": "GRNConnect",
        "ProviderLocationCode": null
    },
    {
        "ProviderHotelId": "467062",
        "ProviderFamily": "HotelBeds",
        "ProviderLocationCode": "EVN"
    },
    {
        "ProviderHotelId": "AM10000057",
        "ProviderFamily": "MGHoliday",
        "ProviderLocationCode": "AM-EVN"
    },
    {
        "ProviderHotelId": "NgXw",
        "ProviderFamily": "Rakuten",
        "ProviderLocationCode": null
    },
    {
        "ProviderHotelId": "1437195",
        "ProviderFamily": "TBO",
        "ProviderLocationCode": "143896"
    }
]