[
    {
        "ProviderHotelId": "10306366",
        "ProviderFamily": "Agoda",
        "ProviderLocationCode": null
    },
    {
        "ProviderHotelId": "2533025",
        "ProviderFamily": "DOTW",
        "ProviderLocationCode": "192958"
    },
    {
        "ProviderHotelId": "42192228",
        "ProviderFamily": "EAN",
        "ProviderLocationCode": null
    },
    {
        "ProviderHotelId": "2084432",
        "ProviderFamily": "GRNConnect",
        "ProviderLocationCode": null
    },
    {
        "ProviderHotelId": "870751",
        "ProviderFamily": "GoGlobal",
        "ProviderLocationCode": null
    },
    {
        "ProviderHotelId": "716334",
        "ProviderFamily": "HotelBeds",
        "ProviderLocationCode": "OF1"
    },
    {
        "ProviderHotelId": "tKtH",
        "ProviderFamily": "Rakuten",
        "ProviderLocationCode": null
    },
    {
        "ProviderHotelId": "5000801",
        "ProviderFamily": "TBO",
        "ProviderLocationCode": "138229"
    }
]